LICENSE
README.md
sqlmeshsm/__init__.py
sqlmeshsm/__main__.py
sqlmeshsm/hooks/__init__.py
sqlmeshsm/hooks/drop_masking_policy.py
sqlmeshsm/hooks/helper.py
sqlmeshsm/hooks/main.py
sqlmeshsm/hooks/queries/drop_masking_policy.sql
sqlmeshsm/hooks/queries/fetch_masking_policy_references.sql
sqlmeshsm/hooks/queries/unset_masking_policy.sql
sqlmeshsm/macros/__init__.py
sqlmeshsm/macros/apply_masking_policy.py
sqlmeshsm/macros/create_masking_policy.py
sqlmeshsm/main.py
sqlmeshsm-0.1.0b5.dist-info/LICENSE
sqlmeshsm-0.1.0b5.dist-info/METADATA
sqlmeshsm-0.1.0b5.dist-info/WHEEL
sqlmeshsm-0.1.0b5.dist-info/entry_points.txt
sqlmeshsm-0.1.0b5.dist-info/RECORD
