Metadata-Version: 2.1
Name: sqlmeshsm
Version: 0.1.0b5
Summary: SQLMesh macros used for ❄️ Dynamic Masking Policies implementation ✏️, and the Snowflake Hooker CLI (hook) ⭐
Home-page: https://github.com/datnguye/sqlmesh-snow-mask
License: MIT
Keywords: flake8,markdown,lint
Author: Dat Nguyen
Author-email: datnguyen.it09@gmail.com
Requires-Python: >=3.9,<4.0
Classifier: Environment :: Console
Classifier: License :: OSI Approved :: MIT License
Classifier: Operating System :: OS Independent
Classifier: Programming Language :: Python :: 3
Classifier: Programming Language :: Python :: 3.9
Classifier: Programming Language :: Python :: 3.10
Classifier: Programming Language :: Python :: 3.11
Classifier: Topic :: Software Development :: Documentation
Classifier: Topic :: Software Development :: Libraries :: Python Modules
Classifier: Topic :: Software Development :: Quality Assurance
Requires-Dist: click (>=8.1.7,<9.0.0)
Requires-Dist: snowflake-connector-python (>=3.1.1,<4.0.0)
Requires-Dist: sqlmesh (>=0.31,<0.32)
Project-URL: Repository, https://github.com/datnguye/sqlmesh-snow-mask
